sendme/__init__.py
sendme/__version__.py
sendme/cli.py
sendme/config.py
sendme/main.py
sendme-2024.9.28.dist-info/METADATA
sendme-2024.9.28.dist-info/WHEEL
sendme-2024.9.28.dist-info/entry_points.txt
sendme-2024.9.28.dist-info/licenses/LICENSE
sendme-2024.9.28.dist-info/RECORD
